rantence/__init__.py
rantence-6.0.0.dist-info/LICENSE.txt
rantence-6.0.0.dist-info/METADATA
rantence-6.0.0.dist-info/WHEEL
rantence-6.0.0.dist-info/top_level.txt
rantence-6.0.0.dist-info/RECORD
