Metadata-Version: 2.1
Name: rantence
Version: 6.0.0
Summary: A Python package that creates random sentences.
Home-page: https://github.com/Cryptos1337/RanTence-Py
Author: Cryptos & Cuet
Author-email: jenkzzjenkzz@protonmail.com
License: UNKNOWN
Platform: UNKNOWN
Classifier: Development Status :: 3 - Alpha
Classifier: Programming Language :: Python :: 3.7
Classifier: License :: OSI Approved :: MIT License
Classifier: Operating System :: OS Independent
Requires-Python: >=3.7
